rgrpc/__init__.py
rgrpc/client.py
rgrpc/reflected_method.py
rgrpc-2023.11.12.dist-info/METADATA
rgrpc-2023.11.12.dist-info/WHEEL
rgrpc-2023.11.12.dist-info/licenses/LICENSE
rgrpc-2023.11.12.dist-info/RECORD
