Metadata-Version: 2.1
Name: rgrpc
Version: 2023.11.12
Summary: A simple to use Python gRPC Reflection Client
Project-URL: Homepage, https://codeberg.org/viridianforge/rgprc
Project-URL: Bug Tracker, https://codeberg.org/viridianforge/rgprc/issues
Author-email: Wayne Manselle <wayne@viridianforge.tech>
License: Apache 2.0
License-File: LICENSE
Keywords: client,grpc,reflection
Classifier: Development Status :: 3 - Alpha
Classifier: Intended Audience :: Developers
Classifier: License :: OSI Approved :: Apache Software License
Classifier: Programming Language :: Python :: 3.8
Requires-Python: >=3.8
Requires-Dist: cryptography>=39.0.1
Requires-Dist: google-api-core>=2.9.0
Requires-Dist: grpcio-reflection>=1.53.0
Requires-Dist: grpcio>=1.53.0
Provides-Extra: dev
Requires-Dist: gprcio-tools; extra == 'dev'
Requires-Dist: grpc-stubs; extra == 'dev'
Requires-Dist: mypy; extra == 'dev'
Requires-Dist: pre-commit; extra == 'dev'
Requires-Dist: pytest; extra == 'dev'
Requires-Dist: ruff; extra == 'dev'
Requires-Dist: types-protobuf; extra == 'dev'
